certbot_dns_ionos/__init__.py
certbot_dns_ionos/ionos.py
certbot_dns_ionos/test_ionos.py
certbot_dns_ionos_cloud-1.0.0.dist-info/LICENSE
certbot_dns_ionos_cloud-1.0.0.dist-info/METADATA
certbot_dns_ionos_cloud-1.0.0.dist-info/WHEEL
certbot_dns_ionos_cloud-1.0.0.dist-info/entry_points.txt
certbot_dns_ionos_cloud-1.0.0.dist-info/top_level.txt
certbot_dns_ionos_cloud-1.0.0.dist-info/RECORD
