Metadata-Version: 2.1
Name: certbot-dns-ionos-cloud
Version: 1.0.0
Summary: Certbot DNS Authenticator plugin for IONOS
Home-page: https://github.com/ionos-cloud/certbot-dns-ionos-cloud
Author: IONOS Cloud DNS team
Author-email: paas-dns@ionos.com
License: Apache License 2.0
Classifier: Development Status :: 5 - Production/Stable
Classifier: Environment :: Plugins
Classifier: Intended Audience :: System Administrators
Classifier: License :: OSI Approved :: Apache Software License
Classifier: Operating System :: POSIX :: Linux
Classifier: Programming Language :: Python
Classifier: Programming Language :: Python :: 3
Classifier: Topic :: Internet :: Name Service (DNS)
Classifier: Topic :: Security
Classifier: Topic :: Security :: Cryptography
Classifier: Topic :: System :: Networking
Classifier: Topic :: System :: Systems Administration
Classifier: Topic :: Utilities
Requires-Python: >=2.7, !=3.0.*, !=3.1.*, !=3.2.*, !=3.3.*
License-File: LICENSE
Requires-Dist: acme >=2.9.0
Requires-Dist: certbot >=2.9.0
Requires-Dist: setuptools
Requires-Dist: requests
Requires-Dist: mock
